{
    "$schema": "http://json-schema.org/draft-07/schema",
    "$id": "device_descriptor_value_changed.json",
    "type": "object",
    "title": "The root schema",
    "description": "The root schema comprises the entire JSON document.",
    "required": [
        "descriptor",
        "device"
    ],
    "properties": {
        "descriptor": {
            "$id": "#/properties/descriptor",
            "type": "object",
            "title": "The descriptor schema",
            "description": "An explanation about the purpose of this instance.",
            "required": [
                "uuid",
                "path",
                "value"
            ],
            "properties": {
                "uuid": {
                    "$id": "#/properties/descriptor/properties/uuid",
                    "type": "string",
                    "title": "The uuid schema",
                    "description": "An explanation about the purpose of this instance."
                },
                "path": {
                    "$id": "#/properties/descriptor/properties/path",
                    "type": "string",
                    "title": "The path schema",
                    "description": "An explanation about the purpose of this instance."
                },
                "value": {
                    "$id": "#/properties/descriptor/properties/value",
                    "type": "array",
                    "title": "The value schema",
                    "description": "An explanation about the purpose of this instance.",
                    "items": {
                        "$id": "#/properties/descriptor/properties/value/items",
                        "anyOf": [
                            {
                                "$id": "#/properties/descriptor/properties/value/items/anyOf/0",
                                "type": "integer",
                                "title": "The first anyOf schema",
                                "description": "An explanation about the purpose of this instance."
                            }
                        ]
                    }
                }
            }
        }
    }
}
